rugivi/config_file_handler.py
rugivi/dialogs.py
rugivi/dir_helper.py
rugivi/icon.ico
rugivi/icon.png
rugivi/print_module_dir.py
rugivi/rugivi.conf
rugivi/rugivi.py
rugivi/rugivi_configurator.py
rugivi/rugivi_image_cache_maintenance.py
rugivi/rugivi_windows.conf
rugivi/selection.py
rugivi/status.py
rugivi/thread_safe_list.py
rugivi/view.py
rugivi/crawlers/first_organic/organic_crawler_first_edition.py
rugivi/exports/world_overlook.py
rugivi/fap_table/fap_table.py
rugivi/fap_table/fap_table_manager.py
rugivi/fap_table/fap_table_view.py
rugivi/fap_table/fap_tables.py
rugivi/image_database_service/image_server_database.py
rugivi/image_service/abstract_cache_filename_generator.py
rugivi/image_service/abstract_streamed_media.py
rugivi/image_service/image_cache.py
rugivi/image_service/image_server.py
rugivi/image_service/streamed_image.py
rugivi/image_service/streamed_mockup.py
rugivi/image_service/video_still_generator.py
rugivi/landmarks/landmark_service.py
rugivi/landmarks/point_of_interest.py
rugivi/landmarks/tour.py
rugivi/world_database_service/abstract_world_database.py
rugivi/world_database_service/world_database.py
rugivi/world_things/abstract_world.py
rugivi/world_things/chunk.py
rugivi/world_things/frame.py
rugivi/world_things/world.py
rugivi-0.6.0a0.dist-info/LICENSE
rugivi-0.6.0a0.dist-info/METADATA
rugivi-0.6.0a0.dist-info/WHEEL
rugivi-0.6.0a0.dist-info/entry_points.txt
rugivi-0.6.0a0.dist-info/top_level.txt
rugivi-0.6.0a0.dist-info/RECORD
