Metadata-Version: 2.1
Name: rugivi
Version: 0.6.0a0
Summary: RuGiVi - Adult Media Landscape Browser
Home-page: https://github.com/pronopython/rugivi
Author: pronopython
Author-email: pronopython@proton.me
License: GNU GENERAL PUBLIC LICENSE V3
License-File: LICENSE
Requires-Dist: pygame >=2.5.2
Requires-Dist: psutil >=5.9.8
Requires-Dist: numpy >=1.26.3
Requires-Dist: sqlitedict >=2.1.0
Requires-Dist: pyshortcuts >=1.9.0
Requires-Dist: Pillow >=9.0.1
Requires-Dist: opencv-python-headless >=4.9.0.80
